[
	{
		"month": "Jan 2015",
		"no_Of_Commits": 2
	},
	{
		"month": "May 2014",
		"no_Of_Commits": 3
	},
	{
		"month": "Apr 2014",
		"no_Of_Commits": 1
	},
	{
		"month": "Mar 2014",
		"no_Of_Commits": 3
	},
	{
		"month": "Feb 2014",
		"no_Of_Commits": 3
	},
	{
		"month": "Jan 2014",
		"no_Of_Commits": 4
	},
	{
		"month": "Dec 2013",
		"no_Of_Commits": 6
	},
	{
		"month": "Nov 2013",
		"no_Of_Commits": 4
	},
	{
		"month": "Oct 2013",
		"no_Of_Commits": 10
	},
	{
		"month": "Sep 2013",
		"no_Of_Commits": 9
	},
	{
		"month": "Aug 2013",
		"no_Of_Commits": 42
	},
	{
		"month": "Jul 2013",
		"no_Of_Commits": 17
	},
	{
		"month": "Jun 2013",
		"no_Of_Commits": 33
	},
	{
		"month": "May 2013",
		"no_Of_Commits": 52
	},
	{
		"month": "Apr 2013",
		"no_Of_Commits": 47
	},
	{
		"month": "Mar 2013",
		"no_Of_Commits": 106
	},
	{
		"month": "Feb 2013",
		"no_Of_Commits": 115
	},
	{
		"month": "Jan 2013",
		"no_Of_Commits": 68
	},
	{
		"month": "Dec 2012",
		"no_Of_Commits": 74
	},
	{
		"month": "Nov 2012",
		"no_Of_Commits": 23
	},
	{
		"month": "Oct 2012",
		"no_Of_Commits": 75
	},
	{
		"month": "Sep 2012",
		"no_Of_Commits": 34
	},
	{
		"month": "Aug 2012",
		"no_Of_Commits": 52
	},
	{
		"month": "Jul 2012",
		"no_Of_Commits": 55
	},
	{
		"month": "Jun 2012",
		"no_Of_Commits": 97
	},
	{
		"month": "May 2012",
		"no_Of_Commits": 70
	},
	{
		"month": "Apr 2012",
		"no_Of_Commits": 50
	},
	{
		"month": "Mar 2012",
		"no_Of_Commits": 74
	},
	{
		"month": "Feb 2012",
		"no_Of_Commits": 155
	},
	{
		"month": "Jan 2012",
		"no_Of_Commits": 27
	},
	{
		"month": "Dec 2011",
		"no_Of_Commits": 17
	},
	{
		"month": "Nov 2011",
		"no_Of_Commits": 6
	},
	{
		"month": "Oct 2011",
		"no_Of_Commits": 9
	},
	{
		"month": "Sep 2011",
		"no_Of_Commits": 12
	},
	{
		"month": "Aug 2011",
		"no_Of_Commits": 7
	},
	{
		"month": "Jul 2011",
		"no_Of_Commits": 12
	},
	{
		"month": "Jun 2011",
		"no_Of_Commits": 3
	},
	{
		"month": "May 2011",
		"no_Of_Commits": 2
	},
	{
		"month": "Apr 2011",
		"no_Of_Commits": 10
	},
	{
		"month": "Mar 2011",
		"no_Of_Commits": 6
	},
	{
		"month": "Feb 2011",
		"no_Of_Commits": 18
	},
	{
		"month": "Jan 2011",
		"no_Of_Commits": 9
	},
	{
		"month": "Dec 2010",
		"no_Of_Commits": 6
	},
	{
		"month": "Nov 2010",
		"no_Of_Commits": 5
	},
	{
		"month": "Oct 2010",
		"no_Of_Commits": 13
	},
	{
		"month": "Sep 2010",
		"no_Of_Commits": 7
	},
	{
		"month": "Aug 2010",
		"no_Of_Commits": 5
	},
	{
		"month": "Jul 2010",
		"no_Of_Commits": 4
	},
	{
		"month": "Jun 2010",
		"no_Of_Commits": 5
	},
	{
		"month": "May 2010",
		"no_Of_Commits": 8
	},
	{
		"month": "Apr 2010",
		"no_Of_Commits": 5
	},
	{
		"month": "Mar 2010",
		"no_Of_Commits": 11
	},
	{
		"month": "Feb 2010",
		"no_Of_Commits": 3
	},
	{
		"month": "Jan 2010",
		"no_Of_Commits": 7
	},
	{
		"month": "Dec 2009",
		"no_Of_Commits": 9
	},
	{
		"month": "Sep 2009",
		"no_Of_Commits": 1
	}
]